OMPython/ModelicaSystem.py
OMPython/OMCSession.py
OMPython/OMParser.py
OMPython/OMTypedParser.py
OMPython/__init__.py
ompython-4.0.0.dist-info/licenses/COPYING
ompython-4.0.0.dist-info/licenses/LICENSE
ompython-4.0.0.dist-info/METADATA
ompython-4.0.0.dist-info/WHEEL
ompython-4.0.0.dist-info/top_level.txt
ompython-4.0.0.dist-info/RECORD
