Metadata-Version: 2.4
Name: OMPython
Version: 4.0.0
Summary: OpenModelica-Python API Interface
Author-email: Anand Kalaiarasi Ganeson <ganan642@student.liu.se>
Maintainer-email: Adeel Asghar <adeel.asghar@liu.se>
License:  This project is part of OpenModelica.
Project-URL: Homepage, http://openmodelica.org/
Project-URL: Documentation, https://openmodelica.org/doc/OpenModelicaUsersGuide/latest/ompython.html
Project-URL: Source Code, https://github.com/OpenModelica/OMPython
Project-URL: Issues, https://github.com/OpenModelica/OMPython/issues
Project-URL: Release Notes, https://github.com/OpenModelica/OMPython/releases
Project-URL: Download, https://pypi.org/project/OMPython/#files
Requires-Python: >=3.10
License-File: LICENSE
License-File: COPYING
Requires-Dist: numpy
Requires-Dist: psutil
Requires-Dist: pyparsing
Requires-Dist: pyzmq
Dynamic: license-file
